binexpr/__init__.py
binexpr/py.typed
binexpr-0.1.0.dist-info/METADATA
binexpr-0.1.0.dist-info/WHEEL
binexpr-0.1.0.dist-info/licenses/LICENSE
binexpr-0.1.0.dist-info/RECORD
