Metadata-Version: 2.4
Name: binexpr
Version: 0.1.0
Summary: Bix is a domain specific language (DSL) for defining, evaluating, saving, and serializing (Bi)nary E(x)pressions.
Author-email: JP Hutchins <jphutchins@gmail.com>
License: MIT License
License-File: LICENSE
Requires-Python: >=3.12
